[
  {
      "sectionId": 1,
      "sectionName": "ContactUs banner",
      "isExistingComponent": true,
      "details": {
          "bannerProperty": 4,
          "bannerDetails": {
              "height": 50,
              "bannerTextBackGroundEnabled": false,
              "textEnabled": true,
              "bannerColor": "#f5f4f1",
              "animation": "noAnimationTemplate",
              "textAlign": "Center",
              "bannerText": "Contact Us",
              "textFontFamily": "Palatino Linotype",
              "textFontStyle": [
                  "B"
              ],
              "subTextFontStyle": [],
              "bannerSubText": "Fill out our contact form below, we aim to answer all requests within 48 hours.",
              "textColor": "#000",
              "bannerTextBackGroundColor": "white",
              "subTextColor": "#4A4D60",
              "textSize": 54,
              "subtextSize": 18
          },
          "inValid": false,
          "isChildError": false
      },
      "script": "themes/bundle/shared-theme/banner.js",
      "selectorDetails": {
          "selector": "phase-ii-banner",
          "inputData": [
              {
                  "selectorInput": "bannerDetails",
                  "handlerInput": "previewDetails.storePageSetup.savedPageContent"
              }
          ],
          "outputData": []
      }
  },
  {
      "sectionId": 2,
      "details": {
          "formSetting": {
              "formOnly": false,
              "showTitle": false,
              "showSubtitle": false,
              "backgroundColor": "#ff7c64",
              "backgroundType": "none",
              "contactusImage": null,
              "imageFill": false,
              "contactusalignment": "center",
              "formFieldAppearence": "outline",
              "inputTextColor": "light",
              "normalLabelColor": "#a49e9e",
              "normalLineColor": "#a49e9e",
              "focusedLabelColor": "#065677",
              "focusedLineColor": "#065677",
              "formFieldDesign": "none",
              "formCard": false,
              "formCardColor": "rgba(0, 0, 0, 0.25)",
              "formCardRadius": 10,
              "formBackground": false,
              "formFieldLabelOut": false,
              "formFieldFill": false,
              "formFieldColor": "rgba(0, 0, 0, 0.25)",
              "suffixIcon": false,
              "nameSplit": false,
              "emailField": true,
              "contactNoField": true,
              "termsAndPrivacy": false,
              "buttonText": "Send",
              "buttonBorderColor": "#000",
              "buttonTextColor": "#fff",
              "buttonColor": "var(--primary-color)",
              "buttonRadius": 5,
              "buttonType": "flat",
              "buttonAlignment": "start",
              "templateName": "templateOne"
          }
      },
      "script": "themes/bundle/shared-theme/common-form.js",
      "selectorDetails": {
          "selector": "phase-ii-common-form",
          "inputData": [
              {
                  "selectorInput": "contactFields",
                  "handlerInput": "previewDetails.storePageSetup.savedPageContent"
              }
          ],
          "outputData": []
      },
      "sectionName": "Contactus form",
      "isExistingComponent": true,
      "sampleData": null
  }
]